aum/__init__.py
aum/aum.py
aum/dataset.py
aum/version.py
aum-1.0.2.dist-info/LICENSE.md
aum-1.0.2.dist-info/METADATA
aum-1.0.2.dist-info/WHEEL
aum-1.0.2.dist-info/top_level.txt
aum-1.0.2.dist-info/zip-safe
aum-1.0.2.dist-info/RECORD
