Metadata-Version: 2.1
Name: aum
Version: 1.0.2
Summary: Library for calculating area under the margin ranking.
Home-page: UNKNOWN
Author: ASAPP Inc.
Author-email: jshapiro@asapp.com
License: UNKNOWN
Platform: UNKNOWN
Requires-Python: >=3.7
Requires-Dist: torch (>=1.3.1)
Requires-Dist: pandas (>=0.25.3)
